btspp/__init__.py
btspp/replay.py
btspp/pytransform/__init__.py
btspp/pytransform/platforms/linux/aarch64/_pytransform.so
btspp/pytransform/platforms/linux/x86_64/_pytransform.so
btspp-0.0.7.dist-info/LICENSE.txt
btspp-0.0.7.dist-info/METADATA
btspp-0.0.7.dist-info/WHEEL
btspp-0.0.7.dist-info/top_level.txt
btspp-0.0.7.dist-info/RECORD
