Metadata-Version: 2.1
Name: btspp
Version: 0.0.7
Summary: Bluetooth SPP Utilities
Home-page: https://pypi.org/project/btspp
Author: Cibo
Author-email: cibo@bio-electric.com
Classifier: Operating System :: POSIX :: Linux
Classifier: Environment :: Console
Classifier: Programming Language :: Python :: 3
Classifier: Programming Language :: Python :: 3 :: Only
Classifier: Programming Language :: Python :: 3.10
Classifier: Topic :: Security
Classifier: Topic :: System :: Networking
Classifier: Topic :: System :: Hardware :: Universal Serial Bus (USB) :: Wireless Controller
Classifier: Intended Audience :: Developers
Classifier: Intended Audience :: Education
Classifier: Intended Audience :: Information Technology
Classifier: Intended Audience :: Science/Research
Classifier: Intended Audience :: System Administrators
Classifier: Intended Audience :: Telecommunications Industry
Classifier: License :: Other/Proprietary License
Requires-Python: ==3.10.*
License-File: LICENSE.txt
Requires-Dist: pybluez (>=0.23)
Requires-Dist: pyshark (>=0.5.3)
Requires-Dist: xpycommon (>=0.0.19)
